vscode/__init__.py
vscode/compiler.py
vscode/config.py
vscode/context.py
vscode/enums.py
vscode/env.py
vscode/extcode.py
vscode/extension.py
vscode/objects.py
vscode/utils.py
vscode/webviews.py
vscode/window.py
vscode/workspace.py
vscode/wsclient.py
vscode.py2-2.0.4.dist-info/LICENSE
vscode.py2-2.0.4.dist-info/METADATA
vscode.py2-2.0.4.dist-info/WHEEL
vscode.py2-2.0.4.dist-info/top_level.txt
vscode.py2-2.0.4.dist-info/RECORD
