Metadata-Version: 2.1
Name: vscode.py2
Version: 2.0.4
Summary: Create VSCode Extensions with python
Home-page: https://github.com/kidandcat/vscode.py
Author: kidandcat
Author-email: kidandcat@gmail.com
Project-URL: Issue tracker, https://github.com/kidandcat/vscode.py/issues
Classifier: Programming Language :: Python :: 3
Classifier: Development Status :: 4 - Beta
Classifier: Intended Audience :: Developers
Classifier: License :: OSI Approved :: MIT License
Classifier: Operating System :: OS Independent
Classifier: Topic :: Internet
Classifier: Topic :: Software Development :: Libraries
Classifier: Topic :: Software Development :: Libraries :: Python Modules
Classifier: Topic :: Utilities
Requires-Python: >=3.8
License-File: LICENSE
Requires-Dist: websockets
